scmcallib/__init__.py
scmcallib/_version.py
scmcallib/distributions.py
scmcallib/metrics.py
scmcallib/parameterset.py
scmcallib/transforms.py
scmcallib/tuningcore.py
scmcallib/utils.py
scmcallib/finder/__init__.py
scmcallib/finder/base.py
scmcallib/finder/distribution.py
scmcallib/finder/point_estimate.py
scmcallib/mat4py/__init__.py
scmcallib/mat4py/loadmat.py
scmcallib/mat4py/savemat.py
scmcallib/optimiser/__init__.py
scmcallib/optimiser/base.py
scmcallib/optimiser/bayesopt.py
scmcallib/optimiser/scipy.py
scmcallib/plot/__init__.py
scmcallib/plot/summary_plot.py
scmcallib/scm/__init__.py
scmcallib/scm/ar5ir.py
scmcallib/scm/base.py
scmcallib/scm/magicc.py
scmcallib-0.5.1.dist-info/METADATA
scmcallib-0.5.1.dist-info/WHEEL
scmcallib-0.5.1.dist-info/top_level.txt
scmcallib-0.5.1.dist-info/RECORD
