Metadata-Version: 2.1
Name: scmcallib
Version: 0.5.1
Summary: Perform calibration for simple climate models
Home-page: https://gitlab.com/magicc/scmcallib
Author: Jared Lewis,Zebedee Nicholls,Matthias Mengel
Author-email: jared.lewis@climate-energy-college.org,zebedee.nicholls@climate-energy-college.org,matthias.mengel@pik-potsdam.de
License: UNKNOWN
Keywords: calibration,tuning,simple climate model,reduced complexity climate model,data processing
Platform: UNKNOWN
Classifier: Development Status :: 3 - Alpha
Classifier: Intended Audience :: Science/Research
Classifier: Natural Language :: English
Classifier: Programming Language :: Python :: 3
Classifier: Programming Language :: Python :: 3.7
Classifier: Topic :: Scientific/Engineering :: Atmospheric Science
Requires-Dist: numpy
Requires-Dist: pandas
Requires-Dist: matplotlib (>=2.0.0)
Requires-Dist: scmdata (>=0.2.2)
Requires-Dist: pymagicc (>=2.0.0b6)
Requires-Dist: scikit-learn
Requires-Dist: tqdm
Requires-Dist: bayesian-optimization
Provides-Extra: deploy
Requires-Dist: twine (>=2.0.0) ; extra == 'deploy'
Requires-Dist: setuptools (>=38.6.0) ; extra == 'deploy'
Requires-Dist: wheel (>=0.31.0) ; extra == 'deploy'
Provides-Extra: dev
Requires-Dist: flake8 (>=3.7.0) ; extra == 'dev'
Requires-Dist: black ; extra == 'dev'
Requires-Dist: codecov ; extra == 'dev'
Requires-Dist: pytest-cov ; extra == 'dev'
Requires-Dist: pytest (<5.0,>=4.0) ; extra == 'dev'
Requires-Dist: notebook ; extra == 'dev'
Requires-Dist: nbval ; extra == 'dev'
Requires-Dist: expectexception ; extra == 'dev'
Requires-Dist: click ; extra == 'dev'
Requires-Dist: sphinx (<2.1,>=1.4) ; extra == 'dev'
Requires-Dist: sphinx-rtd-theme ; extra == 'dev'
Requires-Dist: sphinx-click ; extra == 'dev'
Requires-Dist: twine (>=2.0.0) ; extra == 'dev'
Requires-Dist: setuptools (>=38.6.0) ; extra == 'dev'
Requires-Dist: wheel (>=0.31.0) ; extra == 'dev'
Provides-Extra: docs
Requires-Dist: sphinx (<2.1,>=1.4) ; extra == 'docs'
Requires-Dist: sphinx-rtd-theme ; extra == 'docs'
Requires-Dist: sphinx-click ; extra == 'docs'
Provides-Extra: mcmc
Requires-Dist: pymc3 ; extra == 'mcmc'
Provides-Extra: notebooks
Requires-Dist: notebook ; extra == 'notebooks'
Requires-Dist: nbval ; extra == 'notebooks'
Requires-Dist: expectexception ; extra == 'notebooks'
Requires-Dist: click ; extra == 'notebooks'
Provides-Extra: tests
Requires-Dist: codecov ; extra == 'tests'
Requires-Dist: pytest-cov ; extra == 'tests'
Requires-Dist: pytest (<5.0,>=4.0) ; extra == 'tests'
